<?xml version="1.0" encoding="utf-8"?>
<LanguageData>
  <INI.Name>更多需求條信息</INI.Name>

  <INI.Food.Hungry>{0}后感到餓</INI.Food.Hungry>
  <INI.Food.Ravenous>{0}后非常餓</INI.Food.Ravenous>
  <INI.Food.Malnourished>{0}后營養不良</INI.Food.Malnourished>

  <INI.Rest.Rested>{0}后睡飽</INI.Rest.Rested>
  <INI.Rest.Tired>{0}后感到昏昏欲睡</INI.Rest.Tired>
  <INI.Rest.VeryTired>{0}后感到疲憊不堪</INI.Rest.VeryTired>
  <INI.Rest.Exhausted>{0}后精疲力盡</INI.Rest.Exhausted>

  <INI.Joy.High>{0}后滿意娛樂</INI.Joy.High>
  <INI.Joy.Satisfied>{0}后無需娛樂</INI.Joy.Satisfied>
  <INI.Joy.Low>{0}后需要娛樂</INI.Joy.Low>
  <INI.Joy.VeryLow>{0}后缺乏娛樂</INI.Joy.VeryLow>
  <INI.Joy.Empty>{0}后渴望娛樂</INI.Joy.Empty>
</LanguageData>
